zxtaputils/__init__.py
zxtaputils/bas2asc.py
zxtaputils/bas2tokens.py
zxtaputils/basic_tokens.py
zxtaputils/tap2basic.py
zxtaputils/tapextract.py
zxtaputils/tapify.py
zxtaputils/tapinfo.py
zxtaputils/tapsplit.py
zxtaputils/util.py
zxtaputils-1.0.0.data/scripts/bas2tap
zxtaputils-1.0.0.data/scripts/tap2bas
zxtaputils-1.0.0.data/scripts/tapextract
zxtaputils-1.0.0.data/scripts/tapify
zxtaputils-1.0.0.data/scripts/tapinfo
zxtaputils-1.0.0.data/scripts/tapsplit
zxtaputils-1.0.0.dist-info/DESCRIPTION.rst
zxtaputils-1.0.0.dist-info/LICENSE.txt
zxtaputils-1.0.0.dist-info/METADATA
zxtaputils-1.0.0.dist-info/RECORD
zxtaputils-1.0.0.dist-info/WHEEL
zxtaputils-1.0.0.dist-info/metadata.json
zxtaputils-1.0.0.dist-info/top_level.txt
